{
    "GRI 200": false,
    "GRI 201": {
        "page": "40.txt",
        "context_before": "DICHIARAZIONE CONSOLIDATA DI CARATTERE NON FINANZIARIO 2019 |  2020 GRUPPO CREVAL | 3. APPENDICE GRI STANDARD",
        "context_after": "PERFORMANCE ECONOMICA 2016 GRI 401 OCCUPAZIONE 2016 GRI 103: MANAGEMENT APPROACH 2016 GRI 404 FORMAZIONE ED EDUCAZIONE 2016 GRI 103:",
        "context_sentiment": "neutral",
        "context_subjectivity": "obj"
    },
    "GRI 202": false,
    "GRI 203": false,
    "GRI 204": {
        "page": "39.txt",
        "context_before": "102-54 Dichiarazione sulla rendicontazione in conformita ai GRI Standards 102-55 Indice dei contenuti GRI 102-56 Assurance esterna PRATICHE DI APPROVVIGIONAMENTO",
        "context_after": "PRATICHE DI FORNITURA 2016 204-1 Proporzione di spesa verso fornitori locali PERFORMANCE ECONOMICA GRI 201: PERFORMANCE ECONOMICA 2016 TEMI MATERIAL!",
        "context_sentiment": "neutral",
        "context_subjectivity": "obj"
    },
    "GRI 205": {
        "page": "40.txt",
        "context_before": "GRI 401 OCCUPAZIONE 2016 GRI 103: MANAGEMENT APPROACH 2016 GRI 404 FORMAZIONE ED EDUCAZIONE 2016 GRI 103: MANAGEMENT APPROACH 2016",
        "context_after": "ANTI- CORRUZIONE 2016 GRI 103: MANAGEMENT APPROACH 2016 GRI 301 RISORSE MATERIALI 2016 GRI 302 ENERGIA 2016 GRI 303 ACQUA",
        "context_sentiment": "neutral",
        "context_subjectivity": "obj"
    },
    "GRI 206": false,
    "GRI 207": false,
    "GRI 201-1": false,
    "GRI 201-2": false,
    "GRI 201-3": false,
    "GRI 201-4": false,
    "GRI 202-1": false,
    "GRI 202-2": false,
    "GRI 203-1": false,
    "GRI 203-2": false,
    "GRI 204-1": false,
    "GRI 205-1": false,
    "GRI 205-2": false,
    "GRI 205-3": false,
    "GRI 206-1": false,
    "GRI 207-1": false,
    "GRI 207-2": false,
    "GRI 207-3": false,
    "GRI 207-4": false,
    "201-1": {
        "page": "39.txt",
        "context_before": "G4 FINANCIAL SECTOR DISCLOSURES GRI 103: MANAGEMENT APPROACH 2016 GRI 418 PRIVACY DEI CLIENTI 2016 GRI 103: MANAGEMENT APPROACH 2016",
        "context_after": "Valore economico direttamente generato e distribuito OFFERTA COMMERCIALE DI QUALITA 103-1 Spiegazione del tema materiale e del relativo perimetro 103-2",
        "context_sentiment": "neutral",
        "context_subjectivity": "obj"
    },
    "201-2": false,
    "201-3": {
        "page": "40.txt",
        "context_before": "GRI 306 RIFIUTI ED EFFLUENTI 2016 GRI 103: MANAGEMENT APPROACH 2016 GRI 405 DIVERSITA E PARI OPPORTUNITA 2016 80 DISCLOSURE",
        "context_after": "Piani pensionistici a benefici definiti e altri piani di pensionamento 401-2 Benefit previsti per i dipendenti a tempo pieno, ma",
        "context_sentiment": "neutral",
        "context_subjectivity": "subj"
    },
    "201-4": false,
    "202-1": false,
    "202-2": false,
    "203-1": false,
    "203-2": false,
    "204-1": {
        "page": "9.txt",
        "context_before": "nuovi criteri allin- terno del Manuale degli Approvvigiona- menti di Gruppo (screening etico, sociale e ambientale). Kpi di performance GRI",
        "context_after": "Proporzione di spesa verso fornitori locali Proporzione di spesa verso fornitori locali 2017 Budget di spesa per i fornitori locali",
        "context_sentiment": "neutral",
        "context_subjectivity": "obj"
    },
    "205-1": {
        "page": "40.txt",
        "context_before": "materiale e del relativo perimetro 103-2 La modalita di gestione e le sue componenti 103-3 Valutazione delle modalita di gestione",
        "context_after": "Operazioni valutate per i rischi legati alla corruzione 205-2 Comunicazione e formazione in materia di politiche e procedure anticorruzione 205-3",
        "context_sentiment": "neutral",
        "context_subjectivity": "obj"
    },
    "205-2": {
        "page": "40.txt",
        "context_before": "gestione e le sue componenti 103-3 Valutazione delle modalita di gestione 205-1 Operazioni valutate per i rischi legati alla corruzione",
        "context_after": "Comunicazione e formazione in materia di politiche e procedure anticorruzione 205-3 Episodi di corruzione accertati e azioni intraprese IMPATTI AMBIENTALI",
        "context_sentiment": "neg",
        "context_subjectivity": "subj"
    },
    "205-3": {
        "page": "40.txt",
        "context_before": "205-1 Operazioni valutate per i rischi legati alla corruzione 205-2 Comunicazione e formazione in materia di politiche e procedure anticorruzione",
        "context_after": "Episodi di corruzione accertati e azioni intraprese IMPATTI AMBIENTALI DIRETTI 103-1 Spiegazione del tema materiale e del relativo perimetro 103-2",
        "context_sentiment": "neg",
        "context_subjectivity": "subj"
    },
    "206-1": false,
    "207-1": false,
    "207-2": false,
    "207-3": false,
    "207-4": false,
    "GRI 300": false,
    "GRI 301": {
        "page": "40.txt",
        "context_before": "404 FORMAZIONE ED EDUCAZIONE 2016 GRI 103: MANAGEMENT APPROACH 2016 GRI 205 ANTI- CORRUZIONE 2016 GRI 103: MANAGEMENT APPROACH 2016",
        "context_after": "RISORSE MATERIALI 2016 GRI 302 ENERGIA 2016 GRI 303 ACQUA ED EFFLUENTI 2016 GRI 305 EMISSIONI 2016 GRI 306 RIFIUTI",
        "context_sentiment": "neutral",
        "context_subjectivity": "obj"
    },
    "GRI 302": {
        "page": "40.txt",
        "context_before": "GRI 103: MANAGEMENT APPROACH 2016 GRI 205 ANTI- CORRUZIONE 2016 GRI 103: MANAGEMENT APPROACH 2016 GRI 301 RISORSE MATERIALI 2016",
        "context_after": "ENERGIA 2016 GRI 303 ACQUA ED EFFLUENTI 2016 GRI 305 EMISSIONI 2016 GRI 306 RIFIUTI ED EFFLUENTI 2016 GRI 103:",
        "context_sentiment": "neutral",
        "context_subjectivity": "obj"
    },
    "GRI 303": {
        "page": "40.txt",
        "context_before": "2016 GRI 205 ANTI- CORRUZIONE 2016 GRI 103: MANAGEMENT APPROACH 2016 GRI 301 RISORSE MATERIALI 2016 GRI 302 ENERGIA 2016",
        "context_after": "ACQUA ED EFFLUENTI 2016 GRI 305 EMISSIONI 2016 GRI 306 RIFIUTI ED EFFLUENTI 2016 GRI 103: MANAGEMENT APPROACH 2016 GRI",
        "context_sentiment": "neutral",
        "context_subjectivity": "obj"
    },
    "GRI 304": false,
    "GRI 305": {
        "page": "40.txt",
        "context_before": "GRI 103: MANAGEMENT APPROACH 2016 GRI 301 RISORSE MATERIALI 2016 GRI 302 ENERGIA 2016 GRI 303 ACQUA ED EFFLUENTI 2016",
        "context_after": "EMISSIONI 2016 GRI 306 RIFIUTI ED EFFLUENTI 2016 GRI 103: MANAGEMENT APPROACH 2016 GRI 405 DIVERSITA E PARI OPPORTUNITA 2016",
        "context_sentiment": "neutral",
        "context_subjectivity": "obj"
    },
    "GRI 306": {
        "page": "40.txt",
        "context_before": "2016 GRI 301 RISORSE MATERIALI 2016 GRI 302 ENERGIA 2016 GRI 303 ACQUA ED EFFLUENTI 2016 GRI 305 EMISSIONI 2016",
        "context_after": "RIFIUTI ED EFFLUENTI 2016 GRI 103: MANAGEMENT APPROACH 2016 GRI 405 DIVERSITA E PARI OPPORTUNITA 2016 80 DISCLOSURE 201-3 Piani",
        "context_sentiment": "neutral",
        "context_subjectivity": "obj"
    },
    "GRI 307": false,
    "GRI 308": false,
    "GRI 301-1": false,
    "GRI 301-2": false,
    "GRI 301-3": false,
    "GRI 302-1": false,
    "GRI 302-2": false,
    "GRI 302-3": false,
    "GRI 302-4": false,
    "GRI 302-5": false,
    "GRI 303-1": false,
    "GRI 303-2": false,
    "GRI 303-3": false,
    "GRI 303-4": false,
    "GRI 303-5": false,
    "GRI 304-1": false,
    "GRI 304-2": false,
    "GRI 304-3": false,
    "GRI 304-4": false,
    "GRI 305-1": false,
    "GRI 305-2": false,
    "GRI 305-3": false,
    "GRI 305-4": false,
    "GRI 305-5": false,
    "GRI 305-6": false,
    "GRI 305-7": false,
    "GRI 306-1": false,
    "GRI 306-2": false,
    "GRI 306-3": false,
    "GRI 306-4": false,
    "GRI 306-5": false,
    "GRI 307-1": false,
    "GRI 308-1": false,
    "GRI 308-2": false,
    "301-1": {
        "page": "40.txt",
        "context_before": "materiale e del relativo perimetro 103-2 La modalita di gestione e le sue componenti 103-3 Valutazione delle modalita di gestione",
        "context_after": "Materiali utilizzati per peso o volume 301-2 Materiali utilizzati che provengono da riciclo 302-1 Energia consumata all'interno dell'organizzazione 302-4 Riduzione",
        "context_sentiment": "neutral",
        "context_subjectivity": "obj"
    },
    "301-2": {
        "page": "40.txt",
        "context_before": "modalita di gestione e le sue componenti 103-3 Valutazione delle modalita di gestione 301-1 Materiali utilizzati per peso o volume",
        "context_after": "Materiali utilizzati che provengono da riciclo 302-1 Energia consumata all'interno dell'organizzazione 302-4 Riduzione del consumo di energia 303-3 Prelievo idrico",
        "context_sentiment": "neutral",
        "context_subjectivity": "obj"
    },
    "301-3": false,
    "302-1": {
        "page": "40.txt",
        "context_before": "103-3 Valutazione delle modalita di gestione 301-1 Materiali utilizzati per peso o volume 301-2 Materiali utilizzati che provengono da riciclo",
        "context_after": "Energia consumata all'interno dell'organizzazione 302-4 Riduzione del consumo di energia 303-3 Prelievo idrico 305-1 Emissioni dirette di GHG (Scope 1)",
        "context_sentiment": "neutral",
        "context_subjectivity": "obj"
    },
    "302-2": false,
    "302-3": false,
    "302-4": {
        "page": "40.txt",
        "context_before": "gestione 301-1 Materiali utilizzati per peso o volume 301-2 Materiali utilizzati che provengono da riciclo 302-1 Energia consumata all'interno dell'organizzazione",
        "context_after": "Riduzione del consumo di energia 303-3 Prelievo idrico 305-1 Emissioni dirette di GHG (Scope 1) 305-2 Emissioni indirette di GHG",
        "context_sentiment": "neutral",
        "context_subjectivity": "obj"
    },
    "302-5": false,
    "303-1": false,
    "303-2": false,
    "303-3": {
        "page": "40.txt",
        "context_before": "o volume 301-2 Materiali utilizzati che provengono da riciclo 302-1 Energia consumata all'interno dell'organizzazione 302-4 Riduzione del consumo di energia",
        "context_after": "Prelievo idrico 305-1 Emissioni dirette di GHG (Scope 1) 305-2 Emissioni indirette di GHG da consumi energetici (Scope 2) :",
        "context_sentiment": "neutral",
        "context_subjectivity": "obj"
    },
    "303-4": false,
    "303-5": false,
    "304-1": false,
    "304-2": false,
    "304-3": false,
    "304-4": false,
    "305-1": {
        "page": "40.txt",
        "context_before": "Materiali utilizzati che provengono da riciclo 302-1 Energia consumata all'interno dell'organizzazione 302-4 Riduzione del consumo di energia 303-3 Prelievo idrico",
        "context_after": "Emissioni dirette di GHG (Scope 1) 305-2 Emissioni indirette di GHG da consumi energetici (Scope 2) : 305-3 Altre emissioni",
        "context_sentiment": "neutral",
        "context_subjectivity": "obj"
    },
    "305-2": {
        "page": "40.txt",
        "context_before": "Energia consumata all'interno dell'organizzazione 302-4 Riduzione del consumo di energia 303-3 Prelievo idrico 305-1 Emissioni dirette di GHG (Scope 1)",
        "context_after": "Emissioni indirette di GHG da consumi energetici (Scope 2) : 305-3 Altre emissioni indirette di GHG (Scope 3) 305-5 Riduzione",
        "context_sentiment": "neutral",
        "context_subjectivity": "obj"
    },
    "305-3": {
        "page": "40.txt",
        "context_before": "Prelievo idrico 305-1 Emissioni dirette di GHG (Scope 1) 305-2 Emissioni indirette di GHG da consumi energetici (Scope 2) :",
        "context_after": "Altre emissioni indirette di GHG (Scope 3) 305-5 Riduzione delle emissioni di GHG 306-2 Rifiuti per tipo e metodo di",
        "context_sentiment": "neutral",
        "context_subjectivity": "obj"
    },
    "305-4": false,
    "305-5": {
        "page": "40.txt",
        "context_before": "1) 305-2 Emissioni indirette di GHG da consumi energetici (Scope 2) : 305-3 Altre emissioni indirette di GHG (Scope 3)",
        "context_after": "Riduzione delle emissioni di GHG 306-2 Rifiuti per tipo e metodo di smaltimento RISPETTO DEI DIRITTI UMANI 103-1 Spiegazione del",
        "context_sentiment": "neutral",
        "context_subjectivity": "obj"
    },
    "305-6": false,
    "305-7": false,
    "306-1": false,
    "306-2": {
        "page": "40.txt",
        "context_before": "da consumi energetici (Scope 2) : 305-3 Altre emissioni indirette di GHG (Scope 3) 305-5 Riduzione delle emissioni di GHG",
        "context_after": "Rifiuti per tipo e metodo di smaltimento RISPETTO DEI DIRITTI UMANI 103-1 Spiegazione del tema materiale e del relativo perimetro",
        "context_sentiment": "neutral",
        "context_subjectivity": "obj"
    },
    "306-3": false,
    "306-4": false,
    "306-5": false,
    "307-1": false,
    "308-1": false,
    "308-2": false,
    "GRI 400": false,
    "GRI 401": {
        "page": "40.txt",
        "context_before": "DI CARATTERE NON FINANZIARIO 2019 |  2020 GRUPPO CREVAL | 3. APPENDICE GRI STANDARD GRI 201 PERFORMANCE ECONOMICA 2016",
        "context_after": "OCCUPAZIONE 2016 GRI 103: MANAGEMENT APPROACH 2016 GRI 404 FORMAZIONE ED EDUCAZIONE 2016 GRI 103: MANAGEMENT APPROACH 2016 GRI 205",
        "context_sentiment": "neutral",
        "context_subjectivity": "obj"
    },
    "GRI 402": false,
    "GRI 403": false,
    "GRI 404": {
        "page": "40.txt",
        "context_before": "CREVAL | 3. APPENDICE GRI STANDARD GRI 201 PERFORMANCE ECONOMICA 2016 GRI 401 OCCUPAZIONE 2016 GRI 103: MANAGEMENT APPROACH 2016",
        "context_after": "FORMAZIONE ED EDUCAZIONE 2016 GRI 103: MANAGEMENT APPROACH 2016 GRI 205 ANTI- CORRUZIONE 2016 GRI 103: MANAGEMENT APPROACH 2016 GRI",
        "context_sentiment": "neutral",
        "context_subjectivity": "obj"
    },
    "GRI 405": {
        "page": "40.txt",
        "context_before": "303 ACQUA ED EFFLUENTI 2016 GRI 305 EMISSIONI 2016 GRI 306 RIFIUTI ED EFFLUENTI 2016 GRI 103: MANAGEMENT APPROACH 2016",
        "context_after": "DIVERSITA E PARI OPPORTUNITA 2016 80 DISCLOSURE 201-3 Piani pensionistici a benefici definiti e altri piani di pensionamento 401-2 Benefit",
        "context_sentiment": "neutral",
        "context_subjectivity": "obj"
    },
    "GRI 406": false,
    "GRI 407": false,
    "GRI 408": false,
    "GRI 409": false,
    "GRI 410": false,
    "GRI 411": false,
    "GRI 412": false,
    "GRI 413": false,
    "GRI 414": false,
    "GRI 415": false,
    "GRI 416": false,
    "GRI 417": {
        "page": "39.txt",
        "context_before": "Proporzione di spesa verso fornitori locali PERFORMANCE ECONOMICA GRI 201: PERFORMANCE ECONOMICA 2016 TEMI MATERIAL! GRI 103: MANAGEMENT APPROACH 2016",
        "context_after": "PUBBLICITA ED INFORMATIVE 2016 GRI 103: MANAGEMENT APPROACH 2016 NON GRI GRI 103: MANAGEMENT APPROACH 2016 G4 FINANCIAL SECTOR DISCLOSURES",
        "context_sentiment": "neutral",
        "context_subjectivity": "obj"
    },
    "GRI 418": {
        "page": "39.txt",
        "context_before": "103: MANAGEMENT APPROACH 2016 NON GRI GRI 103: MANAGEMENT APPROACH 2016 G4 FINANCIAL SECTOR DISCLOSURES GRI 103: MANAGEMENT APPROACH 2016",
        "context_after": "PRIVACY DEI CLIENTI 2016 GRI 103: MANAGEMENT APPROACH 2016 201-1 Valore economico direttamente generato e distribuito OFFERTA COMMERCIALE DI QUALITA",
        "context_sentiment": "neutral",
        "context_subjectivity": "obj"
    },
    "GRI 419": false,
    "GRI 401-1": false,
    "GRI 401-2": false,
    "GRI 401-3": false,
    "GRI 402-1": false,
    "GRI 403-1": false,
    "GRI 403-2": false,
    "GRI 403-3": false,
    "GRI 403-4": false,
    "GRI 403-5": false,
    "GRI 403-6": false,
    "GRI 403-7": false,
    "GRI 403-8": false,
    "GRI 403-9": false,
    "GRI 403-10": false,
    "GRI 404-1": false,
    "GRI 404-2": {
        "page": "24.txt",
        "context_before": "cesso e della metodologia, semplicita ope- rativa e chiarezza di lettura - il dettaglio dell'attivita  declinato allinterno dellindica- tore",
        "context_after": ". A tutela dei diritti dei lavoratori vengono inol- tre effettuate: = lagestione dellemergenza: tutti gli addet- ti sono stati",
        "context_sentiment": "neutral",
        "context_subjectivity": "subj"
    },
    "GRI 404-3": false,
    "GRI 405-1": false,
    "GRI 405-2": false,
    "GRI 406-1": false,
    "GRI 407-1": false,
    "GRI 408-1": false,
    "GRI 409-1": false,
    "GRI 410-1": false,
    "GRI 411-1": false,
    "GRI 412-1": false,
    "GRI 412-2": false,
    "GRI 412-3": false,
    "GRI 413-1": false,
    "GRI 413-2": false,
    "GRI 414-1": false,
    "GRI 414-2": false,
    "GRI 415-1": false,
    "GRI 416-1": false,
    "GRI 416-2": false,
    "GRI 417-1": false,
    "GRI 417-2": false,
    "GRI 417-3": false,
    "GRI 418-1": false,
    "GRI 419-1": false,
    "401-1": false,
    "401-2": {
        "page": "40.txt",
        "context_before": "GRI 405 DIVERSITA E PARI OPPORTUNITA 2016 80 DISCLOSURE 201-3 Piani pensionistici a benefici definiti e altri piani di pensionamento",
        "context_after": "Benefit previsti per i dipendenti a tempo pieno, ma non per i dipendenti part-time 0 con contratto a tempo determinato",
        "context_sentiment": "neg",
        "context_subjectivity": "subj"
    },
    "401-3": false,
    "402-1": false,
    "403-1": false,
    "403-2": false,
    "403-3": false,
    "403-4": false,
    "403-5": false,
    "403-6": false,
    "403-7": false,
    "403-8": false,
    "403-9": false,
    "403-10": false,
    "404-1": {
        "page": "40.txt",
        "context_before": "materiale e del relativo perimetro 103-2 La modalita di gestione e le sue componenti 103-3 Valutazione delle modalita di gestione",
        "context_after": "Ore medie di formazione annua per dipendente 404-2 Programmi di aggiornamento delle competenze dei dipendenti e programmi di assistenza alla",
        "context_sentiment": "neutral",
        "context_subjectivity": "obj"
    },
    "404-2": {
        "page": "40.txt",
        "context_before": "di gestione e le sue componenti 103-3 Valutazione delle modalita di gestione 404-1 Ore medie di formazione annua per dipendente",
        "context_after": "Programmi di aggiornamento delle competenze dei dipendenti e programmi di assistenza alla transizione 404-3 Percentuale di dipendenti che ricevono una",
        "context_sentiment": "neutral",
        "context_subjectivity": "obj"
    },
    "404-3": {
        "page": "40.txt",
        "context_before": "medie di formazione annua per dipendente 404-2 Programmi di aggiornamento delle competenze dei dipendenti e programmi di assistenza alla transizione",
        "context_after": "Percentuale di dipendenti che ricevono una valutazione periodica delle performance e dello sviluppo professionale LOTTA ALLA CORRUZIONE 103-1 Spiegazione del",
        "context_sentiment": "neutral",
        "context_subjectivity": "obj"
    },
    "405-1": {
        "page": "40.txt",
        "context_before": "materiale e del relativo perimetro 103-2 La modalita di gestione e le sue componenti 103-3 Valutazione delle modalita di gestione",
        "context_after": "Diversita negli organi di governo e tra i dipendenti 405-2 Rapporto dello stipendio base e retribuzione delle donne rispetto agli",
        "context_sentiment": "neutral",
        "context_subjectivity": "obj"
    },
    "405-2": {
        "page": "40.txt",
        "context_before": "e le sue componenti 103-3 Valutazione delle modalita di gestione 405-1 Diversita negli organi di governo e tra i dipendenti",
        "context_after": "Rapporto dello stipendio base e retribuzione delle donne rispetto agli uomini 406-1 Episodi di discriminazione e misure correttive adottate N",
        "context_sentiment": "neutral",
        "context_subjectivity": "obj"
    },
    "406-1": {
        "page": "40.txt",
        "context_before": "negli organi di governo e tra i dipendenti 405-2 Rapporto dello stipendio base e retribuzione delle donne rispetto agli uomini",
        "context_after": "Episodi di discriminazione e misure correttive adottate N PAGINA NOTE/OMISSIONI 47 47 76, 7, 48-49 51 51 52 76, 7,",
        "context_sentiment": "neutral",
        "context_subjectivity": "obj"
    },
    "407-1": false,
    "408-1": false,
    "409-1": false,
    "410-1": false,
    "411-1": false,
    "412-1": false,
    "412-2": false,
    "412-3": false,
    "413-1": false,
    "413-2": false,
    "414-1": false,
    "414-2": false,
    "415-1": false,
    "416-1": false,
    "416-2": false,
    "417-1": {
        "page": "39.txt",
        "context_before": "materiale e del relativo perimetro 103-2 La modalita di gestione e le sue componenti 103-3 Valutazione delle modalita di gestione",
        "context_after": "Requisiti in materia di informazione ed etichettatura di prodotti e servizi 417-2 Episodi di non conformita in materia di informazione",
        "context_sentiment": "neutral",
        "context_subjectivity": "obj"
    },
    "417-2": {
        "page": "39.txt",
        "context_before": "sue componenti 103-3 Valutazione delle modalita di gestione 417-1 Requisiti in materia di informazione ed etichettatura di prodotti e servizi",
        "context_after": "Episodi di non conformita in materia di informazione ed etichettatura di prodotti e servizi 417-3 Casi di non conformita riguardanti",
        "context_sentiment": "neutral",
        "context_subjectivity": "obj"
    },
    "417-3": {
        "page": "39.txt",
        "context_before": "etichettatura di prodotti e servizi 417-2 Episodi di non conformita in materia di informazione ed etichettatura di prodotti e servizi",
        "context_after": "Casi di non conformita riguardanti comunicazioni di marketing INNOVAZIONE DIGITALE AL SERVIZIO DEI CLIENTI 103-1 Spiegazione del tema materiale e",
        "context_sentiment": "neutral",
        "context_subjectivity": "obj"
    },
    "418-1": {
        "page": "39.txt",
        "context_before": "materiale e del relativo perimetro 103-2 La modalita di gestione e le sue componenti 103-3 Valutazione delle modalita di gestione",
        "context_after": "Denunce comprovate riguardanti le violazioni della privacy dei clienti e perdita di dati dei clienti QUALITA DELLA VITA E WELFARE",
        "context_sentiment": "neutral",
        "context_subjectivity": "obj"
    },
    "419-1": false
}